[
  {
    "coord": {
      "lon": 29.2769,
      "lat": 40.655
    },
    "weather": [
      {
        "id": 800,
        "main": "Clear",
        "description": "açık",
        "icon": "01d"
      }
    ],
    "base": "stations",
    "main": {
      "temp": 30.52,
      "feels_like": 34.31,
      "temp_min": 30.52,
      "temp_max": 30.52,
      "pressure": 1008,
      "humidity": 62,
      "sea_level": 1008,
      "grnd_level": 995
    },
    "visibility": 10000,
    "wind": {
      "speed": 1.29,
      "deg": 269,
      "gust": 2.07
    },
    "clouds": {
      "all": 0
    },
    "dt": 1782898485,
    "sys": {
      "type": 2,
      "id": 269771,
      "country": "TR",
      "sunrise": 1782873323,
      "sunset": 1782927463
    },
    "timezone": 10800,
    "id": 738025,
    "name": "Yalova",
    "cod": 200
  },
  {
    "coord": {
      "lon": 28.9833,
      "lat": 41.0351
    },
    "weather": [
      {
        "id": 800,
        "main": "Clear",
        "description": "açık",
        "icon": "01d"
      }
    ],
    "base": "stations",
    "main": {
      "temp": 30.09,
      "feels_like": 30.72,
      "temp_min": 30.09,
      "temp_max": 30.09,
      "pressure": 1009,
      "humidity": 47,
      "sea_level": 1009,
      "grnd_level": 1001
    },
    "visibility": 10000,
    "wind": {
      "speed": 3.4,
      "deg": 26,
      "gust": 4.71
    },
    "clouds": {
      "all": 0
    },
    "dt": 1782898485,
    "sys": {
      "type": 2,
      "id": 2000954,
      "country": "TR",
      "sunrise": 1782873318,
      "sunset": 1782927609
    },
    "timezone": 10800,
    "id": 745042,
    "name": "İstanbul",
    "cod": 200
  },
  {
    "coord": {
      "lon": 32.8543,
      "lat": 39.9199
    },
    "weather": [
      {
        "id": 800,
        "main": "Clear",
        "description": "açık",
        "icon": "01d"
      }
    ],
    "base": "stations",
    "main": {
      "temp": 28.45,
      "feels_like": 27.48,
      "temp_min": 28.45,
      "temp_max": 29.58,
      "pressure": 1008,
      "humidity": 31,
      "sea_level": 1008,
      "grnd_level": 892
    },
    "visibility": 10000,
    "wind": {
      "speed": 3.13,
      "deg": 90,
      "gust": 5.36
    },
    "clouds": {
      "all": 0
    },
    "dt": 1782898369,
    "sys": {
      "type": 2,
      "id": 267643,
      "country": "TR",
      "sunrise": 1782872607,
      "sunset": 1782926461
    },
    "timezone": 10800,
    "id": 323786,
    "name": "Ankara",
    "cod": 200
  },
  {
    "coord": {
      "lon": 29.0833,
      "lat": 40.1667
    },
    "weather": [
      {
        "id": 800,
        "main": "Clear",
        "description": "açık",
        "icon": "01d"
      }
    ],
    "base": "stations",
    "main": {
      "temp": 32.94,
      "feels_like": 39.94,
      "temp_min": 32.94,
      "temp_max": 32.94,
      "pressure": 1008,
      "humidity": 100,
      "sea_level": 1008,
      "grnd_level": 948
    },
    "visibility": 10000,
    "wind": {
      "speed": 2.68,
      "deg": 336,
      "gust": 3.39
    },
    "clouds": {
      "all": 1
    },
    "dt": 1782898485,
    "sys": {
      "type": 2,
      "id": 2098355,
      "country": "TR",
      "sunrise": 1782873465,
      "sunset": 1782927414
    },
    "timezone": 10800,
    "id": 750268,
    "name": "Bursa",
    "cod": 200
  },
  {
    "coord": {
      "lon": 29.9167,
      "lat": 40.9167
    },
    "weather": [
      {
        "id": 800,
        "main": "Clear",
        "description": "açık",
        "icon": "01d"
      }
    ],
    "base": "stations",
    "main": {
      "temp": 30.75,
      "feels_like": 30.46,
      "temp_min": 30.75,
      "temp_max": 30.75,
      "pressure": 1009,
      "humidity": 39,
      "sea_level": 1009,
      "grnd_level": 984
    },
    "visibility": 10000,
    "wind": {
      "speed": 4.22,
      "deg": 9,
      "gust": 2.23
    },
    "clouds": {
      "all": 0
    },
    "dt": 1782898456,
    "sys": {
      "country": "TR",
      "sunrise": 1782873117,
      "sunset": 1782927362
    },
    "timezone": 10800,
    "id": 742865,
    "name": "Kocaeli",
    "cod": 200
  }
]